justcalc/__init__.py
justcalc/calculator.py
justcalc/test_calculator.py
justcalc/.pytest_cache/.gitignore
justcalc/.pytest_cache/CACHEDIR.TAG
justcalc/.pytest_cache/README.md
justcalc/.pytest_cache/v/cache/lastfailed
justcalc/.pytest_cache/v/cache/nodeids
justcalc/.pytest_cache/v/cache/stepwise
justcalc-0.0.1.dist-info/WHEEL
justcalc-0.0.1.dist-info/METADATA
justcalc-0.0.1.dist-info/RECORD
