Metadata-Version: 2.1
Name: justcalc
Version: 0.0.1
Summary: Basic calculator
Author-email: Justin Pakzad <justinpakmusic@gmail.com>
Requires-Python: >=3.7
Classifier: Programming Language :: Python :: 3
Classifier: License :: OSI Approved :: MIT License
Classifier: Operating System :: OS Independent
